humanizer/__init__.py
humanizer/__init__.pyc
humanizer/base.py
humanizer/base.pyc
humanizer/bytesize.py
humanizer/bytesize.pyc
humanizer/duration.py
humanizer/duration.pyc
humanizer/tests/__init__.py
humanizer/tests/__main__.py
humanizer/tests/helper.py
humanizer/tests/test_bytesize.py
humanizer/tests/test_duration.py
humanizer-0.1.0.dist-info/METADATA
humanizer-0.1.0.dist-info/WHEEL
humanizer-0.1.0.dist-info/top_level.txt
humanizer-0.1.0.dist-info/zip-safe
humanizer-0.1.0.dist-info/RECORD
